secret_parametrizer/__init__.py
secret_parametrizer/admin.py
secret_parametrizer/apps.py
secret_parametrizer/models.py
secret_parametrizer/tests.py
secret_parametrizer/views.py
secret_parametrizer/migrations/0001_initial.py
secret_parametrizer/migrations/0002_secretparametrizer_switch.py
secret_parametrizer/migrations/__init__.py
django_secret_parametrizer-0.0.2.dist-info/LICENSE
django_secret_parametrizer-0.0.2.dist-info/METADATA
django_secret_parametrizer-0.0.2.dist-info/WHEEL
django_secret_parametrizer-0.0.2.dist-info/top_level.txt
django_secret_parametrizer-0.0.2.dist-info/RECORD
