Metadata-Version: 2.1
Name: django-secret-parametrizer
Version: 0.0.2
Summary: Keep your secrtes on the DB
Home-page: https://www.example.com/
Author: Diogo Berti
Author-email: diogoberti88@gmail.com
License: BSD-3-Clause
Platform: UNKNOWN
Classifier: Programming Language :: Python :: 3
Classifier: Operating System :: OS Independent
Requires-Python: >=3.6
License-File: LICENSE
